{"1 8":{"name":"mortal","first":true},"2 8":{"name":"mortal","first":true},"3 8":{"name":"mortal","first":true},"4 8":{"name":"mortal","first":true},"5 8":{"name":"mortal","first":true},"6 8":{"name":"mortal","first":true},"0 9":{"name":"guardian","lastMove":-10,"rate":3,"pillar":true},"6 9":{"name":"guardian","lastMove":-10,"rate":3,"pillar":true},"1 9":{"name":"restless","lastMove":-10,"rate":5},"5 9":{"name":"restless","lastMove":-10,"rate":5},"2 9":{"name":"sling","lastMove":-10,"rate":7},"4 9":{"name":"sling","lastMove":-10,"rate":7},"3 9":{"name":"core"},"0 5":{"name":"mortal","first":false}}