{"3 1":{"name":"mortal","first":true},"7 1":{"name":"mortal","first":true},"0 0":{"name":"horses","pillar":true},"7 0":{"name":"horses","pillar":true},"6 0":{"name":"guardian","lastMove":-10,"rate":3},"2 0":{"name":"bishop"},"5 0":{"name":"bishop"},"3 0":{"name":"sling","lastMove":-10,"rate":7},"4 0":{"name":"core"},"0 2":{"name":"mortal","first":false},"1 2":{"name":"mortal","first":false},"2 2":{"name":"guardian","lastMove":-10,"rate":3,"first":false},"4 3":{"name":"mortal","first":false},"3 2":{"name":"mortal","first":false},"6 2":{"name":"mortal","first":false}}